README.rst
setup.py
pyodesiutils/__init__.py
pyodesiutils.egg-info/PKG-INFO
pyodesiutils.egg-info/SOURCES.txt
pyodesiutils.egg-info/dependency_links.txt
pyodesiutils.egg-info/requires.txt
pyodesiutils.egg-info/top_level.txt