Metadata-Version: 1.1
Name: pyodesiutils
Version: 0.0.4
Summary: Helper for ODESI xml DDI documentation file
Home-page: https://github.com/guinslym/pyodesi_utils
Author: Guinsly Mondesir
Author-email: guinslym@gmail.com
License: MIT
Keywords: ddi,idd,statcan,survey,xml
Platform: UNKNOWN
Classifier: Programming Language :: Python :: 2.7
Classifier: License :: OSI Approved :: MIT License
Classifier: Programming Language :: Python
